ritpytrading/__init__.py
ritpytrading/_validate_response.py
ritpytrading/assets.py
ritpytrading/cases.py
ritpytrading/news.py
ritpytrading/orders.py
ritpytrading/securities.py
ritpytrading/securities_book.py
ritpytrading/securities_history.py
ritpytrading/submit_cancel_orders.py
ritpytrading/tenders.py
ritpytrading/traders.py
ritpytrading-0.1.6.dist-info/AUTHORS.rst
ritpytrading-0.1.6.dist-info/LICENSE
ritpytrading-0.1.6.dist-info/METADATA
ritpytrading-0.1.6.dist-info/WHEEL
ritpytrading-0.1.6.dist-info/top_level.txt
ritpytrading-0.1.6.dist-info/RECORD
