Metadata-Version: 2.1
Name: ritpytrading
Version: 0.1.6
Summary: Python trading library for the Rotman Interactive Software.
Home-page: https://github.com/SamSamhuns/ritpytrading
Author: Samridha Man Shrestha
Author-email: sms1198@nyu.edu
Maintainer: Samridha Man Shrestha
Maintainer-email: sms1198@nyu.edu
License: Apache Software License 2.0
Keywords: ritpytrading
Platform: UNKNOWN
Classifier: Development Status :: 2 - Pre-Alpha
Classifier: Intended Audience :: Developers
Classifier: License :: OSI Approved :: Apache Software License
Classifier: Operating System :: Microsoft :: Windows
Classifier: Natural Language :: English
Classifier: Programming Language :: Python :: 3
Classifier: Programming Language :: Python :: 3.4
Classifier: Programming Language :: Python :: 3.5
Classifier: Programming Language :: Python :: 3.6
Classifier: Programming Language :: Python :: 3.7
Requires-Dist: requests (==2.21.0)
